congen/__init__.py
congen/__main__.py
congen/exporters/CocoplanExporter.py
congen/exporters/CustomJSONDecoder.py
congen/exporters/CustomJSONEncoder.py
congen/exporters/Exporter.py
congen/exporters/GeoTIFFExporter.py
congen/exporters/__init__.py
congen/importers/GeoTIFFImporter.py
congen/importers/Importer.py
congen/importers/ImporterType.py
congen/importers/__init__.py
congen/layers/DependentLayer.py
congen/layers/Layer.py
congen/layers/LayerType.py
congen/layers/LayerUsage.py
congen/layers/Parameter.py
congen/layers/__init__.py
congen/layers/graphLayers/FullGraphLayer.py
congen/layers/graphLayers/GraphLayer.py
congen/layers/graphLayers/RandomGraphLayer.py
congen/layers/graphLayers/__init__.py
congen/layers/pointLayers/PointLayer.py
congen/layers/pointLayers/RasterPointLayer.py
congen/layers/pointLayers/SimpleRandomPointLayer.py
congen/layers/pointLayers/StratifiedRandomPointLayer.py
congen/layers/pointLayers/__init__.py
congen/layers/pointLayers/clustered/KMeansClusteredPointLayer.py
congen/layers/pointLayers/clustered/WardClusteredPointLayer.py
congen/layers/pointLayers/clustered/__init__.py
congen/layers/rasterLayers/ImportedRasterLayer.py
congen/layers/rasterLayers/NoiseRasterLayer.py
congen/layers/rasterLayers/PerlinNoiseLayer.py
congen/layers/rasterLayers/PointRasterLayer.py
congen/layers/rasterLayers/RasterLayer.py
congen/layers/rasterLayers/SimplexNoiseLayer.py
congen/layers/rasterLayers/__init__.py
congen/ui/LayerListCtrl.py
congen/ui/MainApp.py
congen/ui/MainCanvasPanel.py
congen/ui/MainFrame.py
congen/ui/ValueChoice.py
congen/ui/__init__.py
python-congen-git/gb_output.py
python-congen-git/parse_output.py
python-congen-git/setup.py
python-congen-git/build/lib/congen/__init__.py
python-congen-git/build/lib/congen/__main__.py
python-congen-git/build/lib/congen/main.py
python-congen-git/build/lib/congen/exporters/CocoplanExporter.py
python-congen-git/build/lib/congen/exporters/CustomJSONDecoder.py
ConGen-0.0.5.dist-info/LICENSE
ConGen-0.0.5.dist-info/METADATA
ConGen-0.0.5.dist-info/WHEEL
ConGen-0.0.5.dist-info/entry_points.txt
ConGen-0.0.5.dist-info/top_level.txt
ConGen-0.0.5.dist-info/RECORD
