Metadata-Version: 2.1
Name: ConGen
Version: 0.0.5
Summary: Creating conservation planning datasets intuitively by playing with parameters and getting instant visualized feedback
Author-email: Lukas Rose <public@lrose.de>
License: GNU AFFERO GENERAL PUBLIC LICENSE
Project-URL: Homepage, https://codeberg.org/LukeLR/congen
Project-URL: repository, https://codeberg.org/LukeLR/congen
Project-URL: Bug Tracker, https://codeberg.org/LukeLR/congen/issues
Keywords: conservation planning,ecology,synthetic data,random data,data generation,visualization,interactive
Classifier: Development Status :: 4 - Beta
Classifier: Environment :: X11 Applications
Classifier: Framework :: Matplotlib
Classifier: Intended Audience :: Science/Research
Classifier: Programming Language :: Python :: 3
Classifier: License :: OSI Approved :: GNU Affero General Public License v3
Classifier: Natural Language :: English
Classifier: Topic :: Scientific/Engineering :: Bio-Informatics
Classifier: Topic :: Scientific/Engineering :: Visualization
Classifier: Operating System :: OS Independent
Requires-Python: >=3.7
License-File: LICENSE
Requires-Dist: attrdict3
Requires-Dist: matplotlib
Requires-Dist: wxpython
Requires-Dist: gdal
Requires-Dist: jsonpickle
